openshift/__init__.py
openshift/dynamic/__init__.py
openshift/dynamic/apply.py
openshift/dynamic/client.py
openshift/dynamic/discovery.py
openshift/dynamic/exceptions.py
openshift/dynamic/resource.py
openshift/helper/__init__.py
openshift/helper/hashes.py
openshift/helper/userpassauth.py
scripts/__init__.py
scripts/constants.py
openshift-0.13.2.dist-info/LICENSE
openshift-0.13.2.dist-info/METADATA
openshift-0.13.2.dist-info/WHEEL
openshift-0.13.2.dist-info/top_level.txt
openshift-0.13.2.dist-info/RECORD
