Metadata-Version: 2.1
Name: openshift
Version: 0.13.2
Summary: OpenShift python client
Home-page: https://github.com/openshift/openshift-restclient-python
Author: OpenShift
Author-email: 
License: Apache License Version 2.0
Keywords: Swagger,OpenAPI,Kubernetes,OpenShift
Classifier: Development Status :: 3 - Alpha
Classifier: Topic :: Utilities
Classifier: Intended Audience :: Developers
Classifier: Intended Audience :: Information Technology
Classifier: License :: OSI Approved :: Apache Software License
Classifier: Operating System :: OS Independent
Classifier: Programming Language :: Python
Classifier: Programming Language :: Python :: 2
Classifier: Programming Language :: Python :: 2.7
Classifier: Programming Language :: Python :: 3
Classifier: Programming Language :: Python :: 3.5
License-File: LICENSE
